{
  "source_pipeline": "rss_crypto",
  "raw_title": "XRP jumps 3% as breakout above $1.39 ends early-2026 downtrend",
  "raw_content": "",
  "source_url": "https://www.coindesk.com/markets/2026/03/13/xrp-jumps-3-as-breakout-above-usd1-39-ends-early-2026-downtrend",
  "source_name": "CoinDesk",
  "data_type": "news",
  "domain": "crypto",
  "collected_at": "2026-03-13T04:47:34+00:00",
  "id": "363023fd-c646-4e7f-930b-d6aeb78bb646",
  "generated_title": "",
  "generated_summary": "",
  "generated_analysis": "",
  "tags": [],
  "importance_score": 0,
  "processed_at": "2026-03-13T20:45:23.749406+00:00",
  "market_data": {
    "symbols": [],
    "price_change": {},
    "indicators": {}
  },
  "metadata": {
    "feed_url": "https://www.coindesk.com/arc/outboundfeeds/rss/",
    "category": "crypto",
    "source_type": "media",
    "quality_tier": "high",
    "authority_score": 84
  }
}