{
  "source_pipeline": "rss_tech",
  "raw_title": "Grab 工程实践：将 LRU 升级为 TLRU，Android 图片缓存节省 50MB+",
  "raw_content": "点击查看原文>",
  "source_url": "https://www.infoq.cn/article/yu3vmzOKiqHXhwfXty41?utm_source=rss&utm_medium=article",
  "source_name": "InfoQ CN",
  "data_type": "news",
  "domain": "tech",
  "collected_at": "2026-03-15T22:40:31+00:00",
  "id": "186a9c7e-7fc7-48c3-ae27-aa2966f6160b",
  "generated_title": "",
  "generated_summary": "",
  "generated_analysis": "",
  "tags": [],
  "importance_score": 0,
  "processed_at": "2026-03-15T20:39:21.560121+00:00",
  "market_data": {
    "symbols": [],
    "price_change": {},
    "indicators": {}
  },
  "metadata": {
    "feed_url": "https://www.infoq.cn/feed",
    "category": "tech",
    "source_type": "expert_media",
    "quality_tier": "high",
    "authority_score": 82
  }
}