{
  "source_pipeline": "rss_crypto",
  "raw_title": "Boris Johnson calling Bitcoin a ‘Ponzi’ draws rebuttal from Michael Saylor and others",
  "raw_content": "",
  "source_url": "https://www.coindesk.com/business/2026/03/14/boris-johnson-calling-bitcoin-a-ponzi-draws-rebuttal-from-michael-saylor-and-others",
  "source_name": "CoinDesk",
  "data_type": "news",
  "domain": "crypto",
  "collected_at": "2026-03-14T17:18:37+00:00",
  "id": "2a092928-6f4c-4d07-9fed-106e00054c06",
  "generated_title": "",
  "generated_summary": "",
  "generated_analysis": "",
  "tags": [],
  "importance_score": 0,
  "processed_at": "2026-03-15T16:41:06.417650+00:00",
  "market_data": {
    "symbols": [],
    "price_change": {},
    "indicators": {}
  },
  "metadata": {
    "feed_url": "https://www.coindesk.com/arc/outboundfeeds/rss/",
    "category": "crypto",
    "source_type": "media",
    "quality_tier": "high",
    "authority_score": 84
  }
}