{
  "source_pipeline": "rss_ai",
  "raw_title": "The Power of Power Law: Asymmetry Enables Compositional Reasoning",
  "raw_content": "arXiv:2604.22951v1 Announce Type: new \nAbstract: Natural language data follows a power-law distribution, with most knowledge and skills appearing at very low frequency. While a common intuition suggests that reweighting or curating data towards a uniform distribution may help models better learn these long-tail skills, we find a counterintuitive result: across a wide range of compositional reasoning tasks, such as state tracking and multi-step arithmetic, training under power-law distributions consistently outperforms training under uniform distributions. To understand this advantage, we introduce a minimalist skill-composition task and show that learning under a power-law distribution provably requires significantly less training data. Our theoretical analysis reveals that power law sampling induces a beneficial asymmetry that improves the pathological loss landscape, which enables models to first acquire high-frequency skill compositions with low data complexity, which in turn serves as a stepping stone to efficiently learn rare long-tailed skills. Our results offer an alternative perspective on what constitutes an effective data distribution for training models.",
  "source_url": "https://arxiv.org/abs/2604.22951",
  "source_name": "arXiv cs.AI",
  "data_type": "news",
  "domain": "ai",
  "collected_at": "2026-04-29T04:00:00+00:00",
  "id": "7fffc0da-9bbc-4824-aee4-46c8161bbdc7",
  "generated_title": "",
  "generated_summary": "",
  "generated_analysis": "",
  "tags": [],
  "importance_score": 0,
  "processed_at": "",
  "market_data": {
    "symbols": [],
    "price_change": {},
    "indicators": {}
  },
  "metadata": {
    "feed_url": "https://arxiv.org/rss/cs.AI",
    "category": "ai",
    "source_type": "research_org",
    "quality_tier": "authoritative",
    "authority_score": 90
  }
}