{
  "source_pipeline": "rss_tech",
  "raw_title": "月之暗面创始人重磅判断：今年起 AI 研发模式将剧变，海量Token成研究员标配资源",
  "raw_content": "点击查看原文>",
  "source_url": "https://www.infoq.cn/article/WwJZI3vSu5qKagvDvhwK?utm_source=rss&utm_medium=article",
  "source_name": "InfoQ CN",
  "data_type": "news",
  "domain": "tech",
  "collected_at": "2026-03-26T18:20:59+00:00",
  "id": "8311fecd-08fb-4d2a-ab29-d36dfe92ee87",
  "generated_title": "",
  "generated_summary": "",
  "generated_analysis": "",
  "tags": [],
  "importance_score": 0,
  "processed_at": "2026-03-26T17:13:20.371762+00:00",
  "market_data": {
    "symbols": [],
    "price_change": {},
    "indicators": {}
  },
  "metadata": {
    "feed_url": "https://www.infoq.cn/feed",
    "category": "tech",
    "source_type": "expert_media",
    "quality_tier": "high",
    "authority_score": 82
  }
}