{
  "source_pipeline": "rss_crypto",
  "raw_title": "Coinbase-backed crypto advocacy group unveils 2026 election plan",
  "raw_content": "Following its successes mobilizing crypto-minded voters in 2024, Stand With Crypto said it would prioritize House races in two US states for the midterms.",
  "source_url": "https://cointelegraph.com/news/stand-with-crypto-coinbase-midterm-election-strategy?utm_source=rss_feed&utm_medium=rss&utm_campaign=rss_partner_inbound",
  "source_name": "Cointelegraph",
  "data_type": "news",
  "domain": "crypto",
  "collected_at": "2026-03-26T12:00:00+00:00",
  "id": "8ba85a39-cfb8-4ca9-aa37-25541ec5662b",
  "generated_title": "",
  "generated_summary": "",
  "generated_analysis": "",
  "tags": [],
  "importance_score": 0,
  "processed_at": "2026-03-26T17:13:20.377747+00:00",
  "market_data": {
    "symbols": [],
    "price_change": {},
    "indicators": {}
  },
  "metadata": {
    "feed_url": "https://cointelegraph.com/rss",
    "category": "crypto",
    "source_type": "media",
    "quality_tier": "high",
    "authority_score": 82
  }
}