{
  "source_pipeline": "trending_bilibili",
  "raw_title": "闲鱼里为啥有人卖全家福的？",
  "raw_content": "游戏：不知道叫啥游戏",
  "source_url": "https://www.bilibili.com/video/BV1KwQuBeE8G",
  "source_name": "B站热门",
  "data_type": "news",
  "domain": "general",
  "collected_at": "2026-04-13T13:28:45.268978+00:00",
  "id": "697b00b5-8ec6-4dd1-b158-bc69bd20e9f6",
  "generated_title": "",
  "generated_summary": "",
  "generated_analysis": "",
  "tags": [],
  "importance_score": 0,
  "processed_at": "2026-04-13T13:29:25.732716+00:00",
  "market_data": {
    "symbols": [],
    "price_change": {},
    "indicators": {}
  },
  "metadata": {
    "source_type": "trending",
    "quality_tier": "secondary",
    "authority_score": 65,
    "hot_score": 5588088,
    "platform": "bilibili"
  }
}