{
  "source_pipeline": "rss_tech",
  "raw_title": "特斯拉2月在英国销量大幅下滑",
  "raw_content": "3月5日，研究机构New Automotive公布的数据显示，特斯拉2月在英国售出2208辆汽车，同比下降45.2%。（界面）",
  "source_url": "https://36kr.com/newsflashes/3709575713763718?f=rss",
  "source_name": "36kr",
  "data_type": "news",
  "domain": "tech",
  "collected_at": "2026-03-05T04:55:33+00:00",
  "id": "4e98e825-44a2-4e49-9de0-e360bd5d10e3",
  "generated_title": "",
  "generated_summary": "",
  "generated_analysis": "",
  "tags": [],
  "importance_score": 0,
  "processed_at": "",
  "market_data": {
    "symbols": [],
    "price_change": {},
    "indicators": {}
  },
  "metadata": {}
}