{
  "source_pipeline": "rss_crypto",
  "raw_title": "Ethereum aims to cut bridge times by 98% to 13 seconds with new rule",
  "raw_content": "Ethereum’s FCR aims to reduce bridge times by up to 98%, bringing L1-to-L2 and exchange deposits down to 13 seconds without a hard fork.",
  "source_url": "https://cointelegraph.com/news/ethereum-cuts-bridge-times-98-percent-13-seconds-fast-confirmation-rule?utm_source=rss_feed&utm_medium=rss&utm_campaign=rss_partner_inbound",
  "source_name": "Cointelegraph",
  "data_type": "news",
  "domain": "crypto",
  "collected_at": "2026-03-18T10:18:41+00:00",
  "id": "0839aefb-d3a1-4150-8c11-74ee29da4a78",
  "generated_title": "",
  "generated_summary": "",
  "generated_analysis": "",
  "tags": [],
  "importance_score": 0,
  "processed_at": "2026-03-18T13:43:34.484350+00:00",
  "market_data": {
    "symbols": [],
    "price_change": {},
    "indicators": {}
  },
  "metadata": {
    "feed_url": "https://cointelegraph.com/rss",
    "category": "crypto",
    "source_type": "media",
    "quality_tier": "high",
    "authority_score": 82
  }
}