{
  "source_pipeline": "rss_tech",
  "raw_title": "极客邦启动2026「AI 青禾计划」：QCon & AICon首次向全国高校免费开放",
  "raw_content": "<div align=\"right\"><a href=\"https://www.infoq.cn/article/YVquqorayNjdCRW72xxF?utm_source=rss&amp;utm_medium=article\">点击查看原文></a></div>",
  "source_url": "https://www.infoq.cn/article/YVquqorayNjdCRW72xxF?utm_source=rss&utm_medium=article",
  "source_name": "InfoQ CN",
  "data_type": "news",
  "domain": "tech",
  "collected_at": "2026-03-05T16:12:39+00:00",
  "id": "ec4698e2-ae42-4e41-9187-be14acc09d78",
  "generated_title": "",
  "generated_summary": "",
  "generated_analysis": "",
  "tags": [],
  "importance_score": 0,
  "processed_at": "",
  "market_data": {
    "symbols": [],
    "price_change": {},
    "indicators": {}
  },
  "metadata": {}
}