{
  "source_pipeline": "rss_crypto",
  "raw_title": "Early Ethereum whale rebuilds stack with $19.5M in ETH buys",
  "raw_content": "Early Ethereum whale thomasg.eth is rebuilding his position with $19.5 million in ETH purchases this week, as BitMine’s Tom Lee calls for the end of “crypto winter.”",
  "source_url": "https://cointelegraph.com/news/ethereum-whale-thomasg-eth-buys-19-5m?utm_source=rss_feed&utm_medium=rss&utm_campaign=rss_partner_inbound",
  "source_name": "Cointelegraph",
  "data_type": "news",
  "domain": "crypto",
  "collected_at": "2026-03-21T09:22:44+00:00",
  "id": "21f61a40-bfdb-4bc5-97a0-286017452a4e",
  "generated_title": "",
  "generated_summary": "",
  "generated_analysis": "",
  "tags": [],
  "importance_score": 0,
  "processed_at": "2026-03-22T02:55:03.124336+00:00",
  "market_data": {
    "symbols": [],
    "price_change": {},
    "indicators": {}
  },
  "metadata": {
    "feed_url": "https://cointelegraph.com/rss",
    "category": "crypto",
    "source_type": "media",
    "quality_tier": "high",
    "authority_score": 82
  }
}