{
  "source_pipeline": "rss_tech",
  "raw_title": "MiniMax M2.7 Advances Scalable Agentic Workflows on NVIDIA Platforms for Complex AI Applications",
  "raw_content": "The release of&nbsp;MiniMax M2.7&nbsp;adds enhancements to the popular&nbsp;MiniMax&nbsp;M2.5 model,&nbsp;built for agentic harnesses,...",
  "source_url": "https://developer.nvidia.com/blog/minimax-m2-7-advances-scalable-agentic-workflows-on-nvidia-platforms-for-complex-ai-applications/",
  "source_name": "NVIDIA Developer Blog",
  "data_type": "news",
  "domain": "tech",
  "collected_at": "2026-04-12T01:02:44+00:00",
  "id": "1d7bc157-98ef-43bc-9c62-7e53c9d2cb7e",
  "generated_title": "",
  "generated_summary": "",
  "generated_analysis": "",
  "tags": [],
  "importance_score": 0,
  "processed_at": "2026-04-16T21:00:12.771154+00:00",
  "market_data": {
    "symbols": [],
    "price_change": {},
    "indicators": {}
  },
  "metadata": {
    "feed_url": "https://developer.nvidia.com/blog/feed",
    "category": "tech",
    "source_type": "official",
    "quality_tier": "high",
    "authority_score": 81
  }
}