{
  "source_pipeline": "rss_crypto",
  "raw_title": "Paul Tudor Jones calls bitcoin the 'best inflation hedge,' warns of overvalued stocks",
  "raw_content": "",
  "source_url": "https://www.coindesk.com/markets/2026/04/28/paul-tudor-jones-calls-bitcoin-the-best-inflation-hedge-warns-of-overvalued-stocks",
  "source_name": "CoinDesk",
  "data_type": "news",
  "domain": "crypto",
  "collected_at": "2026-04-28T19:56:15+00:00",
  "id": "29bacc86-759c-475a-a5e3-d82560112496",
  "generated_title": "",
  "generated_summary": "",
  "generated_analysis": "",
  "tags": [],
  "importance_score": 0,
  "processed_at": "",
  "market_data": {
    "symbols": [],
    "price_change": {},
    "indicators": {}
  },
  "metadata": {
    "feed_url": "https://www.coindesk.com/arc/outboundfeeds/rss/",
    "category": "crypto",
    "source_type": "media",
    "quality_tier": "high",
    "authority_score": 84
  }
}