{
  "source_pipeline": "rss_tech",
  "raw_title": "基于AI的机器人攻陷微软、DataDog和CNCF项目中的GitHub Actions工作流",
  "raw_content": "<div align=\"right\"><a href=\"https://www.infoq.cn/article/qj2aLodCUPuLu83qkeVx?utm_source=rss&amp;utm_medium=article\">点击查看原文></a></div>",
  "source_url": "https://www.infoq.cn/article/qj2aLodCUPuLu83qkeVx?utm_source=rss&utm_medium=article",
  "source_name": "InfoQ CN",
  "data_type": "news",
  "domain": "tech",
  "collected_at": "2026-03-23T11:00:00+00:00",
  "id": "78d4cb90-d005-488a-8404-be4e1778471c",
  "generated_title": "",
  "generated_summary": "",
  "generated_analysis": "",
  "tags": [],
  "importance_score": 0,
  "processed_at": "",
  "market_data": {
    "symbols": [],
    "price_change": {},
    "indicators": {}
  },
  "metadata": {
    "feed_url": "https://www.infoq.cn/feed",
    "category": "tech",
    "source_type": "expert_media",
    "quality_tier": "high",
    "authority_score": 82
  }
}