{
  "source_pipeline": "rss_crypto",
  "raw_title": "US admiral calls Bitcoin an instrument for US ‘power projection’",
  "raw_content": "US Navy Admiral Samuel Paparo said Bitcoin’s proof-of-work technology has \"really important\" computer science applications when it comes to cybersecurity.",
  "source_url": "https://cointelegraph.com/news/us-admiral-calls-bitcoin-instrument-us-power-projection?utm_source=rss_feed&utm_medium=rss&utm_campaign=rss_partner_inbound",
  "source_name": "Cointelegraph",
  "data_type": "news",
  "domain": "crypto",
  "collected_at": "2026-04-22T02:14:42+00:00",
  "id": "7fbb925f-a3bc-4e38-9f8d-55b8d7ec0fe5",
  "generated_title": "",
  "generated_summary": "",
  "generated_analysis": "",
  "tags": [],
  "importance_score": 0,
  "processed_at": "2026-04-22T03:29:51.808662+00:00",
  "market_data": {
    "symbols": [],
    "price_change": {},
    "indicators": {}
  },
  "metadata": {
    "feed_url": "https://cointelegraph.com/rss",
    "category": "crypto",
    "source_type": "media",
    "quality_tier": "high",
    "authority_score": 82
  }
}