{
  "source_pipeline": "rss_crypto",
  "raw_title": "North Korean workers have been infiltrating DeFi for 7 years: Researcher",
  "raw_content": "<p style=\"float: right; margin: 0 0 10px 15px; width: 240px;\"><img alt=\"North Korean workers have been infiltrating DeFi for 7 years: Researcher\" class=\"type:primaryImage\" src=\"https://images.cointelegraph.com/images/528_aHR0cHM6Ly9zMy5jb2ludGVsZWdyYXBoLmNvbS91cGxvYWRzLzIwMjYtMDQvMDE5ZDYxMDYtZTU3Ny03YjAxLWI1ZWQtYmU0NmM4YTVjNmI5LmpwZw==.jpg\" /></p><p>Security researcher Taylor Monahan listed at least 40 decentralized finance platforms she claims have been infiltrated by North Korean IT workers at some stage of their lives.</p>",
  "source_url": "https://cointelegraph.com/news/dprk-workers-have-worked-on-countless-protocols-since-defi-summer-cybersec-analyst?utm_source=rss_feed&utm_medium=rss&utm_campaign=rss_partner_inbound",
  "source_name": "Cointelegraph",
  "data_type": "news",
  "domain": "crypto",
  "collected_at": "2026-04-06T06:04:46+00:00",
  "id": "a1f69ec4-e943-42fc-9f06-2659c49c68b2",
  "generated_title": "",
  "generated_summary": "",
  "generated_analysis": "",
  "tags": [],
  "importance_score": 0,
  "processed_at": "",
  "market_data": {
    "symbols": [],
    "price_change": {},
    "indicators": {}
  },
  "metadata": {
    "feed_url": "https://cointelegraph.com/rss",
    "category": "crypto",
    "source_type": "media",
    "quality_tier": "high",
    "authority_score": 82
  }
}