{
  "source_pipeline": "rss_tech",
  "raw_title": "Hasbro says it was hacked, and may take ‘several weeks’ to recover",
  "raw_content": "The American toy-making giant noted that it was continuing to \"implement measures to secure its business operations,\" suggesting that the hackers may still be in the company's systems.",
  "source_url": "https://techcrunch.com/2026/04/01/hasbro-hacked-may-take-several-weeks-to-recover/",
  "source_name": "TechCrunch",
  "data_type": "news",
  "domain": "tech",
  "collected_at": "2026-04-01T14:50:32+00:00",
  "id": "4c1e4ec7-44c0-4829-b456-62e68eae3855",
  "generated_title": "",
  "generated_summary": "",
  "generated_analysis": "",
  "tags": [],
  "importance_score": 0,
  "processed_at": "",
  "market_data": {
    "symbols": [],
    "price_change": {},
    "indicators": {}
  },
  "metadata": {
    "feed_url": "https://techcrunch.com/feed/",
    "category": "tech",
    "source_type": "media",
    "quality_tier": "high",
    "authority_score": 78
  }
}