{
  "source_pipeline": "rss_tech",
  "raw_title": "Why safety regulators closed their investigation into Tesla’s remote parking feature",
  "raw_content": "NHTSA closed its investigation into Tesla's \"Actually Smart Summon\" feature, saying that only a fraction of cases resulted in an incident, and that no incidents resulted in injury. Tesla has also issued a number of software updates.",
  "source_url": "https://techcrunch.com/2026/04/06/tesla-actually-smart-summon-nhtsa-investigation-smart-parking/",
  "source_name": "TechCrunch",
  "data_type": "news",
  "domain": "tech",
  "collected_at": "2026-04-06T18:17:23+00:00",
  "id": "c6abb8c2-26c9-4882-a23a-c93120b3f17d",
  "generated_title": "",
  "generated_summary": "",
  "generated_analysis": "",
  "tags": [],
  "importance_score": 0,
  "processed_at": "2026-04-06T20:51:00.860455+00:00",
  "market_data": {
    "symbols": [],
    "price_change": {},
    "indicators": {}
  },
  "metadata": {
    "feed_url": "https://techcrunch.com/feed/",
    "category": "tech",
    "source_type": "media",
    "quality_tier": "high",
    "authority_score": 78
  }
}