{
  "source_pipeline": "trending_toutiao",
  "raw_title": "宇树科技亚洲首家体验店将落户上海",
  "raw_content": "宇树科技亚洲首家体验店将落户上海",
  "source_url": "https://www.toutiao.com/trending/7622505333801467930/?category_name=topic_innerflow&event_type=hot_board&log_pb=%7B%22category_name%22%3A%22topic_innerflow%22%2C%22cluster_type%22%3A%2210%22%2C%22enter_from%22%3A%22click_category%22%2C%22entrance_hotspot%22%3A%22outside%22%2C%22event_type%22%3A%22hot_board%22%2C%22hot_board_cluster_id%22%3A%227622505333801467930%22%2C%22hot_board_impr_id%22%3A%2220260329150548D9D8E1B483DC335E0844%22%2C%22jump_page%22%3A%22hot_board_page%22%2C%22location%22%3A%22news_hot_card%22%2C%22page_location%22%3A%22hot_board_page%22%2C%22source%22%3A%22trending_tab%22%2C%22style_id%22%3A%2240132%22%2C%22title%22%3A%22%E5%AE%87%E6%A0%91%E7%A7%91%E6%8A%80%E4%BA%9A%E6%B4%B2%E9%A6%96%E5%AE%B6%E4%BD%93%E9%AA%8C%E5%BA%97%E5%B0%86%E8%90%BD%E6%88%B7%E4%B8%8A%E6%B5%B7%22%7D&rank=&style_id=40132&topic_id=7622505333801467930",
  "source_name": "今日头条",
  "data_type": "news",
  "domain": "general",
  "collected_at": "2026-03-29T07:05:48.824795+00:00",
  "id": "97fdec04-3e97-410e-92bd-019621b2a15d",
  "generated_title": "",
  "generated_summary": "",
  "generated_analysis": "",
  "tags": [],
  "importance_score": 0,
  "processed_at": "",
  "market_data": {
    "symbols": [],
    "price_change": {},
    "indicators": {}
  },
  "metadata": {
    "source_type": "trending",
    "quality_tier": "secondary",
    "authority_score": 72,
    "hot_score": "13471471",
    "platform": "toutiao"
  }
}