{
  "source_pipeline": "rss_tech",
  "raw_title": "35 年只卖设计，今天亲自下场造芯！Arm 首款自研芯片发布，Meta 抢下首单",
  "raw_content": "<div align=\"right\"><a href=\"https://www.infoq.cn/article/SKhCim03Cgu5QvflVoba?utm_source=rss&amp;utm_medium=article\">点击查看原文></a></div>",
  "source_url": "https://www.infoq.cn/article/SKhCim03Cgu5QvflVoba?utm_source=rss&utm_medium=article",
  "source_name": "InfoQ CN",
  "data_type": "news",
  "domain": "tech",
  "collected_at": "2026-03-25T11:53:18+00:00",
  "id": "452ce7a7-64f7-482c-88d2-6aa6bf76e86e",
  "generated_title": "",
  "generated_summary": "",
  "generated_analysis": "",
  "tags": [],
  "importance_score": 0,
  "processed_at": "",
  "market_data": {
    "symbols": [],
    "price_change": {},
    "indicators": {}
  },
  "metadata": {
    "feed_url": "https://www.infoq.cn/feed",
    "category": "tech",
    "source_type": "expert_media",
    "quality_tier": "high",
    "authority_score": 82
  }
}