{
  "source_pipeline": "rss_finance",
  "raw_title": "中朝旅客列车恢复运行",
  "raw_content": "2026/03/11 连接中国与朝鲜的旅客列车将于3月12日恢复运行，这是约6年来首次恢复。该线路此前因新冠疫情长期中断。随着来自中国的游客预计增加，这也将为希望获得外汇收入的朝鲜带来利好。 列车预计将运行于两国首都北京—平壤之间，同时也连接作为边境中转站的中国东北辽宁省丹东—平壤线路。 中国外交部10日表示欢迎恢复中朝旅客列车运行，发言人郭嘉昆在记者会上称：“中朝是友好近邻，保持常态化客运列车运营对促进双方人员往来便利化具有重要意义。中方支持双方主管部门加强沟通，为双边人员往来创造更加便利的条件”。 根据朝鲜旅游部门在官方网站公布的“国际列车时刻表”，北京至平壤的运行时间约1天，每周运行4次。",
  "source_url": "http://cn.nikkei.com/politicsaeconomy/politicsasociety/61719-2026-03-11-08-04-31.html?print=1",
  "source_name": "日经中文网",
  "data_type": "news",
  "domain": "finance",
  "collected_at": "2026-03-11T01:08:03+00:00",
  "id": "57357c59-71e5-4b5b-88d2-d92dadf7fd4c",
  "generated_title": "",
  "generated_summary": "",
  "generated_analysis": "",
  "tags": [],
  "importance_score": 0,
  "processed_at": "2026-03-11T08:54:45.978267+00:00",
  "market_data": {
    "symbols": [],
    "price_change": {},
    "indicators": {}
  },
  "metadata": {
    "feed_url": "https://feedx.net/rss/nikkei.xml",
    "category": "finance",
    "source_type": "premium_media",
    "quality_tier": "high",
    "authority_score": 82
  }
}