{
  "source_pipeline": "rss_crypto",
  "raw_title": "UK review recommends crypto donation pause over foreign interference risk",
  "raw_content": "A UK review led by Philip Rycroft recommended a temporary moratorium on crypto political donations until stronger safeguards and statutory guidance are in place.",
  "source_url": "https://cointelegraph.com/news/uk-crypto-donation-pause-foreign-interference-risk?utm_source=rss_feed&utm_medium=rss&utm_campaign=rss_partner_inbound",
  "source_name": "Cointelegraph",
  "data_type": "news",
  "domain": "crypto",
  "collected_at": "2026-03-25T13:46:46+00:00",
  "id": "64013f3e-19f4-414d-9a1b-3d4dc18f8023",
  "generated_title": "",
  "generated_summary": "",
  "generated_analysis": "",
  "tags": [],
  "importance_score": 0,
  "processed_at": "2026-03-25T17:14:42.879297+00:00",
  "market_data": {
    "symbols": [],
    "price_change": {},
    "indicators": {}
  },
  "metadata": {
    "feed_url": "https://cointelegraph.com/rss",
    "category": "crypto",
    "source_type": "media",
    "quality_tier": "high",
    "authority_score": 82
  }
}