{
  "source_pipeline": "rss_tech",
  "raw_title": "This Personality Trait Makes Dreams More Bizarre, Scientists Discover",
  "raw_content": "Scientists analyzed thousands of self-reported dreams and discovered that our sleeping visions are influenced by personality traits and external events, such as the pandemic.",
  "source_url": "https://www.404media.co/this-personality-trait-makes-dreams-more-bizarre-scientists-discover/",
  "source_name": "404 Media",
  "data_type": "news",
  "domain": "tech",
  "collected_at": "2026-05-02T13:00:40+00:00",
  "id": "3c764374-44a9-4c4a-b7bb-f36a8a10edee",
  "generated_title": "",
  "generated_summary": "",
  "generated_analysis": "",
  "tags": [],
  "importance_score": 0,
  "processed_at": "2026-05-02T20:55:08.863963+00:00",
  "market_data": {
    "symbols": [],
    "price_change": {},
    "indicators": {}
  },
  "metadata": {
    "feed_url": "https://www.404media.co/rss",
    "category": "tech",
    "source_type": "media",
    "quality_tier": "high",
    "authority_score": 79
  }
}