{
  "source_pipeline": "rss_tech",
  "raw_title": "Zendesk acquires agentic customer service startup Forethought",
  "raw_content": "Forethought was years ahead of its time and the 2018 winner of TechCrunch Battlefield.",
  "source_url": "https://techcrunch.com/2026/03/11/zendesk-acquires-agentic-customer-service-startup-forethought/",
  "source_name": "TechCrunch",
  "data_type": "news",
  "domain": "tech",
  "collected_at": "2026-03-11T22:41:27+00:00",
  "id": "1293fa26-7735-4ed6-810e-580e35a859e2",
  "generated_title": "",
  "generated_summary": "",
  "generated_analysis": "",
  "tags": [],
  "importance_score": 0,
  "processed_at": "2026-03-12T17:06:52.738627+00:00",
  "market_data": {
    "symbols": [],
    "price_change": {},
    "indicators": {}
  },
  "metadata": {
    "feed_url": "https://techcrunch.com/feed/",
    "category": "tech",
    "source_type": "media",
    "quality_tier": "high",
    "authority_score": 78
  }
}