{
  "source_pipeline": "rss_tech",
  "raw_title": "为应对“AI垃圾”满天飞，arXiv脱离康奈尔大学单独运营",
  "raw_content": "点击查看原文>",
  "source_url": "https://www.infoq.cn/article/Z791iXT2AhuA0Fiz0pcs?utm_source=rss&utm_medium=article",
  "source_name": "InfoQ CN",
  "data_type": "news",
  "domain": "tech",
  "collected_at": "2026-03-20T18:30:58+00:00",
  "id": "0b3ee817-84af-4f33-a0d1-5d15c2b9371e",
  "generated_title": "",
  "generated_summary": "",
  "generated_analysis": "",
  "tags": [],
  "importance_score": 0,
  "processed_at": "2026-03-21T13:06:20.170112+00:00",
  "market_data": {
    "symbols": [],
    "price_change": {},
    "indicators": {}
  },
  "metadata": {
    "feed_url": "https://www.infoq.cn/feed",
    "category": "tech",
    "source_type": "expert_media",
    "quality_tier": "high",
    "authority_score": 82
  }
}